lodstorage/__init__.py
lodstorage/docstring_parser.py
lodstorage/exception_handler.py
lodstorage/linkml.py
lodstorage/linkml_gen.py
lodstorage/lod.py
lodstorage/lod2xml.py
lodstorage/lod_csv.py
lodstorage/mwTable.py
lodstorage/mysql.py
lodstorage/params.py
lodstorage/plot.py
lodstorage/prefix_config.py
lodstorage/prefixes.py
lodstorage/profiler.py
lodstorage/query.py
lodstorage/query_cmd.py
lodstorage/querymain.py
lodstorage/rate_limiter.py
lodstorage/rdf.py
lodstorage/rdf_format.py
lodstorage/sample2.py
lodstorage/schema.py
lodstorage/sparql.py
lodstorage/sql.py
lodstorage/sqlite_api.py
lodstorage/storageconfig.py
lodstorage/sync.py
lodstorage/tabulateCounter.py
lodstorage/uml.py
lodstorage/version.py
lodstorage/yaml_path.py
sampledata/__init__.py
sampledata/dblp.yaml
sampledata/endpoints.yaml
sampledata/endpoints_qlever.yaml
sampledata/example.ttl
sampledata/formats.yaml
sampledata/got.yaml
sampledata/prefixes.yaml
sampledata/queries.yaml
sampledata/royals.yaml
sampledata/royals_linkml_schema.yaml
sampledata/scholia.yaml
sampledata/trulytabular.yaml
sampledata/wf.yaml
sampledata/wikidata.yaml
sampledata/queries/queries_olympics.yaml
sampledata/queries/queries_tiny_wikidatasubsets_claude4_5.yaml
sampledata/queries/queries_tiny_wikidatasubsets_gemini3pro.yaml
sampledata/queries/queries_tiny_wikidatasubsets_gpt5.yaml
sampledata/queries/queries_tiny_wikidatasubsets_grok4.yaml
pylodstorage-0.18.7.dist-info/METADATA
pylodstorage-0.18.7.dist-info/WHEEL
pylodstorage-0.18.7.dist-info/entry_points.txt
pylodstorage-0.18.7.dist-info/licenses/LICENSE
pylodstorage-0.18.7.dist-info/RECORD
