Metadata-Version: 2.4
Name: pyLodStorage
Version: 0.18.7
Summary: python List of Dict (Table) Storage library
Project-URL: Home, https://github.com/WolfgangFahl/pyLodStorage
Project-URL: Documentation, http://wiki.bitplan.com/index.php/PyLoDStorage
Project-URL: Source, https://github.com/WolfgangFahl/pyLodStorage/blob/master/lodstorage/sql.py
Project-URL: IssueTracker, https://github.com/WolfgangFahl/pyLodStorage/issues
Author-email: Wolfgang Fahl <wf@bitplan.com>
Maintainer-email: Wolfgang Fahl <wf@bitplan.com>
License-Expression: Apache-2.0
License-File: LICENSE
Classifier: Programming Language :: Python
Classifier: Programming Language :: Python :: 3.10
Classifier: Programming Language :: Python :: 3.11
Classifier: Programming Language :: Python :: 3.12
Classifier: Programming Language :: Python :: 3.13
Requires-Python: >=3.10
Requires-Dist: dicttoxml2
Requires-Dist: jsonpickle>=4.0.2
Requires-Dist: matplotlib>=3.8.2
Requires-Dist: numpy
Requires-Dist: orjson>=3.9.15
Requires-Dist: pybasemkit>=0.1.3
Requires-Dist: pygments
Requires-Dist: pymysql>=1.1.1
Requires-Dist: pyparsing>=3.1.1
Requires-Dist: python-slugify>=8.0.1
Requires-Dist: pyyaml
Requires-Dist: ratelimit>=2.2.1
Requires-Dist: rdflib>=7.1.0
Requires-Dist: requests>=2.31.0
Requires-Dist: sparqlwrapper>=2.0.0
Requires-Dist: tabulate
Provides-Extra: test
Requires-Dist: green; extra == 'test'
